opencsg/__init__.py
opencsg/rest/__init__.py
opencsg/rest/_base_client.py
opencsg/rest/_base_type.py
opencsg/rest/_client.py
opencsg/rest/_constants.py
opencsg/rest/_exceptions.py
opencsg/rest/_resource.py
opencsg/rest/_type.py
opencsg/rest/_utils.py
opencsg/rest/chatflow/__init__.py
starchain_python_sdk-0.0.3.dist-info/LICENSE
starchain_python_sdk-0.0.3.dist-info/METADATA
starchain_python_sdk-0.0.3.dist-info/WHEEL
starchain_python_sdk-0.0.3.dist-info/top_level.txt
starchain_python_sdk-0.0.3.dist-info/RECORD
